dpks/__init__.py
dpks/annotate_proteins.py
dpks/classification.py
dpks/cli.py
dpks/correction.py
dpks/differential_testing.py
dpks/dpks.py
dpks/feature_selection.py
dpks/imputer.py
dpks/interpretation.py
dpks/normalization.py
dpks/param_search.py
dpks/parsers.py
dpks/plot.py
dpks/quant_matrix.py
dpks/quantification.py
dpks/scaling.py
dpks-0.1.5.dist-info/LICENSE
dpks-0.1.5.dist-info/METADATA
dpks-0.1.5.dist-info/WHEEL
dpks-0.1.5.dist-info/top_level.txt
dpks-0.1.5.dist-info/RECORD
