Metadata-Version: 2.1
Name: dpks
Version: 0.1.5
Summary: Data processing package for the analysis of omics data
Home-page: https://github.com/InfectionMedicineProteomics/DPKS
Author: Aaron Scott
Author-email: Aaron Scott <aaron.scott@med.lu.se>, Erik Hartman <erik.hartman@med.lu.se>, Lars Malmström <lars.malmstrom@med.lu.se>
Project-URL: Homepage, https://github.com/InfectionMedicineProteomics/DPKS
Project-URL: Documentation, https://infectionmedicineproteomics.github.io/DPKS/
Project-URL: Issues, https://github.com/InfectionMedicineProteomics/DPKS/issues
Classifier: Programming Language :: Python :: 3
Classifier: License :: OSI Approved :: MIT License
Classifier: Operating System :: OS Independent
Requires-Python: >=3.8
License-File: LICENSE
Requires-Dist: click
Requires-Dist: numpy
Requires-Dist: numba
Requires-Dist: scipy
Requires-Dist: networkx
Requires-Dist: pandas
Requires-Dist: seaborn
Requires-Dist: anndata
Requires-Dist: scikit-learn
Requires-Dist: statsmodels
Requires-Dist: biopython
Requires-Dist: pytest
Requires-Dist: pytest-runner
Requires-Dist: xgboost
Requires-Dist: shap
Requires-Dist: imbalanced-learn
Requires-Dist: kneed
Requires-Dist: gseapy
Requires-Dist: unipressed
Requires-Dist: jupyterlab
Requires-Dist: inmoose
